README.txt
bootstrap.py
buildout.cfg
ffmpeg.cfg
setup.cfg
setup.py
utilities.patch
versions.cfg
collective/__init__.py
collective.transcode.star.egg-info/PKG-INFO
collective.transcode.star.egg-info/SOURCES.txt
collective.transcode.star.egg-info/dependency_links.txt
collective.transcode.star.egg-info/entry_points.txt
collective.transcode.star.egg-info/namespace_packages.txt
collective.transcode.star.egg-info/not-zip-safe
collective.transcode.star.egg-info/requires.txt
collective.transcode.star.egg-info/top_level.txt
collective/transcode/__init__.py
collective/transcode/star/__init__.py
collective/transcode/star/configure.zcml
collective/transcode/star/crypto.py
collective/transcode/star/interfaces.py
collective/transcode/star/subscribers.py
collective/transcode/star/tests.py
collective/transcode/star/utility.py
collective/transcode/star/version.txt
collective/transcode/star/browser/__init__.py
collective/transcode/star/browser/configure.zcml
collective/transcode/star/browser/controlpanel.py
collective/transcode/star/browser/embed.pt
collective/transcode/star/browser/viewlet.pt
collective/transcode/star/browser/viewlets.py
collective/transcode/star/browser/views.py
collective/transcode/star/browser/images/facebook.png
collective/transcode/star/browser/images/gradient_light.png
collective/transcode/star/browser/images/twitter.png
collective/transcode/star/browser/images/unisubs.png
collective/transcode/star/browser/js/unisubs-widgetizer-inner.js
collective/transcode/star/browser/js/unisubs-widgetizer.js
collective/transcode/star/profiles/default/componentregistry.xml
collective/transcode/star/profiles/default/controlpanel.xml
collective/transcode/star/profiles/default/metadata.xml
collective/transcode/star/profiles/default/registry.xml
docs/CONTRIBUTORS.txt
docs/HISTORY.txt
docs/INSTALL.txt
docs/LICENSE.GPL
docs/LICENSE.txt
patches/async.patch
scripts/jpeg
scripts/mp4-high
scripts/mp4-low
scripts/webm-high
scripts/webm-low