Metadata-Version: 1.0
Name: collective.transcode.star
Version: 0.20
Summary: Transcoding support for Plone video files, using collective.transcode.daemon
Home-page: https://github.com/plumi/collective.transcode.star
Author: https://unweb.me
Author-email: we@unweb.me
License: GPL
Keywords: video transcoding plone ffmpeg flv mp4 ogg
Platform: UNKNOWN
Classifier: Environment :: Web Environment
Classifier: Framework :: Plone
Classifier: Intended Audience :: Developers
Classifier: Intended Audience :: System Administrators
Classifier: Intended Audience :: Other Audience
Classifier: License :: OSI Approved :: GNU General Public License (GPL)
Classifier: Operating System :: OS Independent
Classifier: Programming Language :: Python
Classifier: Topic :: Software Development :: Libraries :: Python Modules
